serunaiAutomation/__init__.py
serunaiAutomation/convert_ide.py
serunaiAutomation/serunaiAutomate.py
serunaiAutomation-2.11.dist-info/LICENSE
serunaiAutomation-2.11.dist-info/METADATA
serunaiAutomation-2.11.dist-info/WHEEL
serunaiAutomation-2.11.dist-info/entry_points.txt
serunaiAutomation-2.11.dist-info/top_level.txt
serunaiAutomation-2.11.dist-info/RECORD
