Metadata-Version: 2.1
Name: serunaiAutomation
Version: 2.11
Summary: Automation Framework for Seamless Testing and Data Extraction
Author: Maimul
Author-email: maimulskates@gmail.com
License-File: LICENSE
Requires-Dist: selenium
Requires-Dist: seleniumbase
Requires-Dist: openpyxl
Requires-Dist: hashlib
Requires-Dist: json
Requires-Dist: csv
Requires-Dist: datetime
Requires-Dist: time
Requires-Dist: random
